cafex_ui/__init__.py
cafex_ui/cafex_ui_config_utils.py
cafex_ui/ui_security.py
cafex_ui/mobile_client/__init__.py
cafex_ui/mobile_client/mobile_client_actions.py
cafex_ui/mobile_client/mobile_driver_factory.py
cafex_ui/mobile_client/mobile_driver_initializer.py
cafex_ui/mobile_client/mobile_utils.py
cafex_ui/web_client/__init__.py
cafex_ui/web_client/browserstack_integration.py
cafex_ui/web_client/keyboard_mouse_actions.py
cafex_ui/web_client/ui_web_driver_initializer.py
cafex_ui/web_client/web_client_enum.py
cafex_ui/web_client/web_driver_factory.py
cafex_ui/web_client/drivers/__init__.py
cafex_ui/web_client/drivers/chrome_driver.py
cafex_ui/web_client/drivers/edge_driver.py
cafex_ui/web_client/drivers/firefox_driver.py
cafex_ui/web_client/drivers/internet_explorer_driver.py
cafex_ui/web_client/drivers/safari_driver.py
cafex_ui/web_client/web_client_actions/__init__.py
cafex_ui/web_client/web_client_actions/base_web_client_actions.py
cafex_ui/web_client/web_client_actions/element_interactions.py
cafex_ui/web_client/web_client_actions/utility_methods.py
cafex_ui/web_client/web_client_actions/webdriver_interactions.py
cafex_ui-1.0.0.dist-info/METADATA
cafex_ui-1.0.0.dist-info/WHEEL
cafex_ui-1.0.0.dist-info/entry_points.txt
cafex_ui-1.0.0.dist-info/top_level.txt
cafex_ui-1.0.0.dist-info/RECORD
