Metadata-Version: 2.4
Name: cafex-ui
Version: 1.0.0
Summary: UI Library
Author-email: QA Automation Team <qa_automation@gmail.com>
Project-URL: Homepage, https://example.com
Project-URL: Documentation, https://readthedocs.org
Project-URL: Repository, https://github.com/me/spam.git
Project-URL: Issues, https://github.com/me/spam/issues
Project-URL: Changelog, https://github.com/me/spam/blob/master/CHANGELOG.md
Keywords: ui,appium,selenium,pytest,automation
Classifier: Programming Language :: Python :: 3
Classifier: Operating System :: OS Independent
Requires-Python: >=3.12
Requires-Dist: cafex-core>=1.0.0
Requires-Dist: selenium==4.26.1
Requires-Dist: Appium-Python-Client==4.0.1
Requires-Dist: browserstack-local==1.2.7
Requires-Dist: opencv-python==4.10.0.84
Requires-Dist: playwright==1.54.0
